README.rst
setup.py
promote/__init__.py
promote/metadata.py
promote/promote.py
promote/promote_json.py
promote/utils.py
promote/validator.py
promote/version.py
promote.egg-info/PKG-INFO
promote.egg-info/SOURCES.txt
promote.egg-info/dependency_links.txt
promote.egg-info/requires.txt
promote.egg-info/top_level.txt